{
  "items": [
    {
      "id": "bohemian-rhapsody-kr",
      "name": "Bohemian Rhapsody",
      "subtitle": "Queen",
      "image": "https://upload.wikimedia.org/wikipedia/en/9/9f/Bohemian_Rhapsody.png"
    },
    {
      "id": "dont-stop-believin-kr",
      "name": "Don't Stop Believin'",
      "subtitle": "Journey",
      "image": "https://upload.wikimedia.org/wikipedia/en/6/66/Don%27t_Stop_Believin%27.jpg"
    },
    {
      "id": "livin-on-a-prayer-kr",
      "name": "Livin' on a Prayer",
      "subtitle": "Bon Jovi",
      "image": "https://upload.wikimedia.org/wikipedia/en/c/c6/LivinOnAPrayer%28hq%29.jpg"
    },
    {
      "id": "sweet-caroline",
      "name": "Sweet Caroline",
      "subtitle": "Neil Diamond",
      "image": "https://upload.wikimedia.org/wikipedia/en/d/dc/Sweet_Caroline_cover.jpg"
    },
    {
      "id": "mr-brightside",
      "name": "Mr. Brightside",
      "subtitle": "The Killers",
      "image": "https://placehold.co/500x500/1a1a2e/8b5cf6?text=Mr.+Brightside"
    },
    {
      "id": "dancing-queen",
      "name": "Dancing Queen",
      "subtitle": "ABBA",
      "image": "https://placehold.co/500x500/1a1a2e/8b5cf6?text=Dancing+Queen"
    },
    {
      "id": "i-want-it-that-way",
      "name": "I Want It That Way",
      "subtitle": "Backstreet Boys",
      "image": "https://upload.wikimedia.org/wikipedia/en/thumb/b/b9/Iwantitthatwaycd.jpg/500px-Iwantitthatwaycd.jpg"
    },
    {
      "id": "total-eclipse-of-the-heart",
      "name": "Total Eclipse of the Heart",
      "subtitle": "Bonnie Tyler",
      "image": "https://placehold.co/500x500/1a1a2e/8b5cf6?text=Total+Eclipse+of+the+Heart"
    },
    {
      "id": "take-me-home-country-roads-kr",
      "name": "Take Me Home, Country Roads",
      "subtitle": "John Denver",
      "image": "https://placehold.co/500x500/1a1a2e/8b5cf6?text=Take+Me+Home%2C+Country+Roads"
    },
    {
      "id": "dont-stop-me-now",
      "name": "Don't Stop Me Now",
      "subtitle": "Queen",
      "image": "https://placehold.co/500x500/1a1a2e/8b5cf6?text=Don't+Stop+Me+Now"
    },
    {
      "id": "build-me-up-buttercup",
      "name": "Build Me Up Buttercup",
      "subtitle": "The Foundations",
      "image": "https://placehold.co/500x500/1a1a2e/8b5cf6?text=Build+Me+Up+Buttercup"
    },
    {
      "id": "since-u-been-gone",
      "name": "Since U Been Gone",
      "subtitle": "Kelly Clarkson",
      "image": "https://placehold.co/500x500/1a1a2e/8b5cf6?text=Since+U+Been+Gone"
    },
    {
      "id": "summer-nights",
      "name": "Summer Nights",
      "subtitle": "Grease",
      "image": "https://placehold.co/500x500/1a1a2e/8b5cf6?text=Summer+Nights"
    },
    {
      "id": "bye-bye-bye",
      "name": "Bye Bye Bye",
      "subtitle": "*NSYNC",
      "image": "https://placehold.co/500x500/1a1a2e/8b5cf6?text=Bye+Bye+Bye"
    },
    {
      "id": "baby-one-more-time",
      "name": "...Baby One More Time",
      "subtitle": "Britney Spears",
      "image": "https://upload.wikimedia.org/wikipedia/en/e/ec/...Baby_One_More_Time_Single.png"
    },
    {
      "id": "wannabe",
      "name": "Wannabe",
      "subtitle": "Spice Girls",
      "image": "https://upload.wikimedia.org/wikipedia/en/6/63/Wannabe_Single.png"
    },
    {
      "id": "somebody-to-love-kr",
      "name": "Somebody to Love",
      "subtitle": "Queen",
      "image": "https://upload.wikimedia.org/wikipedia/en/d/dc/Stlove.jpg"
    },
    {
      "id": "hotel-california-kr",
      "name": "Hotel California",
      "subtitle": "Eagles",
      "image": "https://placehold.co/500x500/1a1a2e/8b5cf6?text=Hotel+California"
    },
    {
      "id": "africa",
      "name": "Africa",
      "subtitle": "Toto",
      "image": "https://upload.wikimedia.org/wikipedia/en/1/1f/Toto_-_Africa.jpg"
    },
    {
      "id": "shake-it-off-kr",
      "name": "Shake It Off",
      "subtitle": "Taylor Swift",
      "image": "https://placehold.co/500x500/1a1a2e/8b5cf6?text=Shake+It+Off"
    },
    {
      "id": "man-i-feel-like-a-woman-kr",
      "name": "Man! I Feel Like a Woman!",
      "subtitle": "Shania Twain",
      "image": "https://placehold.co/500x500/1a1a2e/8b5cf6?text=Man!+I+Feel+Like+a+Woman!"
    },
    {
      "id": "respect",
      "name": "Respect",
      "subtitle": "Aretha Franklin",
      "image": "https://placehold.co/500x500/1a1a2e/8b5cf6?text=Respect"
    },
    {
      "id": "uptown-funk-kr",
      "name": "Uptown Funk",
      "subtitle": "Bruno Mars",
      "image": "https://upload.wikimedia.org/wikipedia/en/a/a7/Mark_Ronson_-_Uptown_Funk_%28feat._Bruno_Mars%29_%28Official_Single_Cover%29.png"
    },
    {
      "id": "i-gotta-feeling",
      "name": "I Gotta Feeling",
      "subtitle": "Black Eyed Peas",
      "image": "https://upload.wikimedia.org/wikipedia/en/f/f4/I_Gotta_Feeling.png"
    },
    {
      "id": "hey-ya",
      "name": "Hey Ya!",
      "subtitle": "OutKast",
      "image": "https://placehold.co/500x500/1a1a2e/8b5cf6?text=Hey+Ya!"
    },
    {
      "id": "aint-no-mountain-kr",
      "name": "Ain't No Mountain High Enough",
      "subtitle": "Marvin Gaye",
      "image": "https://placehold.co/500x500/1a1a2e/8b5cf6?text=Ain't+No+Mountain+High+Enough"
    },
    {
      "id": "hallelujah",
      "name": "Hallelujah",
      "subtitle": "Leonard Cohen",
      "image": "https://placehold.co/500x500/1a1a2e/8b5cf6?text=Hallelujah"
    },
    {
      "id": "piano-man",
      "name": "Piano Man",
      "subtitle": "Billy Joel",
      "image": "https://placehold.co/500x500/1a1a2e/8b5cf6?text=Piano+Man"
    },
    {
      "id": "wonderwall",
      "name": "Wonderwall",
      "subtitle": "Oasis",
      "image": "https://placehold.co/500x500/1a1a2e/8b5cf6?text=Wonderwall"
    },
    {
      "id": "under-pressure-kr",
      "name": "Under Pressure",
      "subtitle": "Queen & David Bowie",
      "image": "https://upload.wikimedia.org/wikipedia/commons/thumb/b/b3/Queen_%26_David_Bowie_-_Under_Pressure.jpeg/500px-Queen_%26_David_Bowie_-_Under_Pressure.jpeg"
    },
    {
      "id": "love-shack",
      "name": "Love Shack",
      "subtitle": "The B-52's",
      "image": "https://placehold.co/500x500/1a1a2e/8b5cf6?text=Love+Shack"
    },
    {
      "id": "take-on-me-kr",
      "name": "Take On Me",
      "subtitle": "a-ha",
      "image": "https://placehold.co/500x500/1a1a2e/8b5cf6?text=Take+On+Me"
    }
  ]
}
