{
  "items": [
    { "id": "spirited-away", "name": "Spirited Away", "image": "https://image.tmdb.org/t/p/w300/placeholder.jpg", "subtitle": "2001 - Studio Ghibli" },
    { "id": "the-lion-king-anim", "name": "The Lion King", "image": "https://image.tmdb.org/t/p/w300/placeholder.jpg", "subtitle": "1994 - Disney" },
    { "id": "toy-story-anim", "name": "Toy Story", "image": "https://image.tmdb.org/t/p/w300/placeholder.jpg", "subtitle": "1995 - Pixar" },
    { "id": "shrek", "name": "Shrek", "image": "https://image.tmdb.org/t/p/w300/placeholder.jpg", "subtitle": "2001 - DreamWorks" },
    { "id": "finding-nemo-anim", "name": "Finding Nemo", "image": "https://image.tmdb.org/t/p/w300/placeholder.jpg", "subtitle": "2003 - Pixar" },
    { "id": "spider-verse", "name": "Spider-Man: Into the Spider-Verse", "image": "https://image.tmdb.org/t/p/w300/placeholder.jpg", "subtitle": "2018 - Sony" },
    { "id": "frozen-anim", "name": "Frozen", "image": "https://image.tmdb.org/t/p/w300/placeholder.jpg", "subtitle": "2013 - Disney" },
    { "id": "wall-e-anim", "name": "WALL-E", "image": "https://image.tmdb.org/t/p/w300/placeholder.jpg", "subtitle": "2008 - Pixar" },
    { "id": "up-anim", "name": "Up", "image": "https://image.tmdb.org/t/p/w300/placeholder.jpg", "subtitle": "2009 - Pixar" },
    { "id": "how-to-train-your-dragon", "name": "How to Train Your Dragon", "image": "https://image.tmdb.org/t/p/w300/placeholder.jpg", "subtitle": "2010 - DreamWorks" },
    { "id": "the-incredibles-anim", "name": "The Incredibles", "image": "https://image.tmdb.org/t/p/w300/placeholder.jpg", "subtitle": "2004 - Pixar" },
    { "id": "ratatouille-anim", "name": "Ratatouille", "image": "https://image.tmdb.org/t/p/w300/placeholder.jpg", "subtitle": "2007 - Pixar" },
    { "id": "coco-anim", "name": "Coco", "image": "https://image.tmdb.org/t/p/w300/placeholder.jpg", "subtitle": "2017 - Pixar" },
    { "id": "inside-out-anim", "name": "Inside Out", "image": "https://image.tmdb.org/t/p/w300/placeholder.jpg", "subtitle": "2015 - Pixar" },
    { "id": "princess-mononoke", "name": "Princess Mononoke", "image": "https://image.tmdb.org/t/p/w300/placeholder.jpg", "subtitle": "1997 - Studio Ghibli" },
    { "id": "beauty-and-the-beast-anim", "name": "Beauty and the Beast", "image": "https://image.tmdb.org/t/p/w300/placeholder.jpg", "subtitle": "1991 - Disney" },
    { "id": "aladdin-anim", "name": "Aladdin", "image": "https://image.tmdb.org/t/p/w300/placeholder.jpg", "subtitle": "1992 - Disney" },
    { "id": "kung-fu-panda", "name": "Kung Fu Panda", "image": "https://image.tmdb.org/t/p/w300/placeholder.jpg", "subtitle": "2008 - DreamWorks" },
    { "id": "the-iron-giant", "name": "The Iron Giant", "image": "https://image.tmdb.org/t/p/w300/placeholder.jpg", "subtitle": "1999 - Warner Bros" },
    { "id": "monsters-inc-anim", "name": "Monsters, Inc.", "image": "https://image.tmdb.org/t/p/w300/placeholder.jpg", "subtitle": "2001 - Pixar" },
    { "id": "shrek-2", "name": "Shrek 2", "image": "https://image.tmdb.org/t/p/w300/placeholder.jpg", "subtitle": "2004 - DreamWorks" },
    { "id": "moana-anim", "name": "Moana", "image": "https://image.tmdb.org/t/p/w300/placeholder.jpg", "subtitle": "2016 - Disney" },
    { "id": "akira", "name": "Akira", "image": "https://image.tmdb.org/t/p/w300/placeholder.jpg", "subtitle": "1988 - TMS" },
    { "id": "the-nightmare-before-christmas-anim", "name": "The Nightmare Before Christmas", "image": "https://image.tmdb.org/t/p/w300/placeholder.jpg", "subtitle": "1993 - Disney" },
    { "id": "soul-anim", "name": "Soul", "image": "https://image.tmdb.org/t/p/w300/placeholder.jpg", "subtitle": "2020 - Pixar" },
    { "id": "zootopia-anim", "name": "Zootopia", "image": "https://image.tmdb.org/t/p/w300/placeholder.jpg", "subtitle": "2016 - Disney" },
    { "id": "the-lego-movie", "name": "The Lego Movie", "image": "https://image.tmdb.org/t/p/w300/placeholder.jpg", "subtitle": "2014 - Warner Bros" },
    { "id": "across-the-spider-verse", "name": "Across the Spider-Verse", "image": "https://image.tmdb.org/t/p/w300/placeholder.jpg", "subtitle": "2023 - Sony" },
    { "id": "tangled-anim", "name": "Tangled", "image": "https://image.tmdb.org/t/p/w300/placeholder.jpg", "subtitle": "2010 - Disney" },
    { "id": "puss-in-boots-last-wish", "name": "Puss in Boots: The Last Wish", "image": "https://image.tmdb.org/t/p/w300/placeholder.jpg", "subtitle": "2022 - DreamWorks" },
    { "id": "megamind", "name": "Megamind", "image": "https://image.tmdb.org/t/p/w300/placeholder.jpg", "subtitle": "2010 - DreamWorks" },
    { "id": "coraline", "name": "Coraline", "image": "https://image.tmdb.org/t/p/w300/placeholder.jpg", "subtitle": "2009 - Laika" }
  ]
}
