{
  "items": [
    { "id": "pepperoni", "name": "Pepperoni", "subtitle": "Classic meat topping" },
    { "id": "mushrooms", "name": "Mushrooms", "subtitle": "Sliced or diced" },
    { "id": "sausage", "name": "Italian Sausage", "subtitle": "Crumbled or sliced" },
    { "id": "extra-cheese", "name": "Extra Cheese", "subtitle": "More mozzarella" },
    { "id": "green-peppers", "name": "Green Peppers", "subtitle": "Bell peppers" },
    { "id": "onions", "name": "Onions", "subtitle": "Red or white" },
    { "id": "black-olives", "name": "Black Olives", "subtitle": "Sliced" },
    { "id": "bacon", "name": "Bacon", "subtitle": "Crispy pieces" },
    { "id": "pineapple", "name": "Pineapple", "subtitle": "The controversial one" },
    { "id": "ham", "name": "Ham", "subtitle": "Diced or sliced" },
    { "id": "jalapenos", "name": "Jalapenos", "subtitle": "Spicy kick" },
    { "id": "spinach", "name": "Spinach", "subtitle": "Fresh or cooked" },
    { "id": "fresh-basil", "name": "Fresh Basil", "subtitle": "Classic Italian" },
    { "id": "buffalo-chicken", "name": "Buffalo Chicken", "subtitle": "Spicy chicken" },
    { "id": "bbq-chicken", "name": "BBQ Chicken", "subtitle": "Sweet & smoky" },
    { "id": "anchovies", "name": "Anchovies", "subtitle": "Love 'em or hate 'em" }
  ]
}
